{
    "skybox":
    {
        "vert":"skybox.vert.glsl",
        "frag":"skybox.frag.glsl"
    },
    "terrain":
    {
        "vert":"terrain.vert.glsl",
        "frag":"terrain.frag.glsl"
    },
    "basic":
    {
        "normals":
        {
            "vert":"basic_normals.vert.glsl",
            "frag":"basic_normals.frag.glsl"
        },
        "positions":
        {
            "vert":"basic_pos.vert.glsl",
            "frag":"basic_pos.frag.glsl"
        },
        "tex coords":
        {
            "vert":"basic_uv.vert.glsl",
            "frag":"basic_uv.frag.glsl"
        },
        "simple n dot l":
        {
            "vert":"basic_n_dot_l.vert.glsl",
            "frag":"basic_n_dot_l.frag.glsl"
        }
    },
    "post_process":
    {
        "vert":"post_process_FSQ.vert.glsl",
        "frag":
        [
            "post_process_brighten.frag.glsl",
            "post_process_invert.frag.glsl",
            "post_process_grayscale.frag.glsl",
            "post_process_quantize.frag.glsl",
            "post_process_edge_detection.frag.glsl",
            "post_process_color_cycle.frag.glsl"
        ]
    },
    "material":
    {
        "vert":
        [
            "material_scene.vert.glsl",
            "material_rotates.vert.glsl",
            "material_wave_x.vert.glsl",
            "material_wave_y.vert.glsl",
            "material_wave_z.vert.glsl"
        ],
        "geo":
        [
            "material_pass_through.geo",
            "material_pass_sin_offset.geo",
            "material_gen_normals.geo"
        ],
        "frag":
        [
            "material_normals.frag.glsl",
            "material_texture.frag.glsl",
            "material_reflective.frag.glsl",
            "material_n_dot_l.frag.glsl"
        ]
    }
}